easy_vitessce/__init__.py
easy_vitessce/colors.py
easy_vitessce/configure_plots.py
easy_vitessce/data.py
easy_vitessce/spatialdata_plot.py
easy_vitessce/widget.py
easy_vitessce-0.0.9.dist-info/METADATA
easy_vitessce-0.0.9.dist-info/WHEEL
easy_vitessce-0.0.9.dist-info/licenses/LICENSE
easy_vitessce-0.0.9.dist-info/RECORD
