Metadata-Version: 2.4
Name: easy_vitessce
Version: 0.0.9
Summary: A package to easily use Vitessce to create interactive plots for single-cell data
Project-URL: repository, https://github.com/vitessce/easy_vitessce
Author: HIDIVE Lab, Selena Luo
License: MIT License
License-File: LICENSE
Classifier: Operating System :: OS Independent
Classifier: Programming Language :: Python :: 3
Requires-Python: >=3.10
Requires-Dist: anndata>=0.11.4
Requires-Dist: black>=21.11b1
Requires-Dist: dask[dataframe]==2024.11.1
Requires-Dist: distributed<=2024.11.2
Requires-Dist: donfig>=0.3.1
Requires-Dist: numcodecs<0.16.0,>=0.5.7
Requires-Dist: numpy>=1.21.2
Requires-Dist: pandas>=1.1.2
Requires-Dist: scanpy>=1.11.3
Requires-Dist: scipy>=1.2.1
Requires-Dist: spatialdata-plot>=0.2.7
Requires-Dist: spatialdata>=0.3.0
Requires-Dist: vitessce[all]>=3.7.9
Requires-Dist: xarray<=2025.3.0,>=2024.10.0
Requires-Dist: zarr<3,>=2.5.0
Provides-Extra: dev
Requires-Dist: jupyter; extra == 'dev'
Requires-Dist: jupyterlab; extra == 'dev'
Requires-Dist: pytest>=8.4.1; extra == 'dev'
Requires-Dist: pyyaml; extra == 'dev'
Provides-Extra: docs
Requires-Dist: myst-parser; extra == 'docs'
Requires-Dist: nbsphinx; extra == 'docs'
Requires-Dist: sphinx; extra == 'docs'
Requires-Dist: sphinx-book-theme; extra == 'docs'
Requires-Dist: sphinx-copybutton; extra == 'docs'
